verilog/assignments/2/convolution/conv.v
module conv(
    input [3:0] x[7:0],
    input [3:0] h[7:0],
    output reg [3:0] out[14:0]
);

    always @(*) begin
        for (integer i = 0; i < 15; i = i + 1) out[i] = 0;

        for(integer i = 0; i < 8; i = i + 1) begin
            for(integer j = 0; j < 8; j = j + 1) begin
                out[i + j] = out[i + j] + x[i]*h[j];
            end
        end
    end
endmodule

verilog/assignments/2/convolution/tb_conv.v
`timescale 1ns / 1ps

module tb_conv;
    reg [3:0] x[7:0];
    reg [3:0] h[7:0];
    wire [3:0] out[14:0];

    conv dut(.x(x), .h(h), .out(out));

    initial begin
        $dumpfile("conv.vcd");
        $dumpvars(0, tb_conv);
        $monitor("> TestCase\nx = [%d %d %d %d %d %d %d %d]\nh = [%d %d %d %d %d %d %d %d]\nx*h = [%d %d %d %d %d %d %d %d]\n", x[0], x[1], x[2], x[3], x[4], x[5], x[6], x[7], h[0], h[1], h[2], h[3], h[4], h[5], h[6], h[7], out[0], out[1], out[2], out[3], out[4], out[5], out[6], out[7]);
        x[0] = 4'd1; x[1] = 4'd2; x[2] = 4'd3; x[3] = 4'd4;
        x[4] = 4'd0; x[5] = 4'd1; x[6] = 4'd0; x[7] = 4'd1;
        h[0] = 4'd1; h[1] = 4'd0; h[2] = 4'd1; h[3] = 4'd0;
        h[4] = 4'd1; h[5] = 4'd0; h[6] = 4'd1; h[7] = 4'd0;
        #10;

        x[0] = 4'd1; x[1] = 4'd1; x[2] = 4'd1; x[3] = 4'd1;
        x[4] = 4'd1; x[5] = 4'd1; x[6] = 4'd1; x[7] = 4'd1;
        h[0] = 4'd1; h[1] = 4'd1; h[2] = 4'd1; h[3] = 4'd1;
        h[4] = 4'd1; h[5] = 4'd1; h[6] = 4'd1; h[7] = 4'd1;
        #10;

        x[0] = 4'd1; x[1] = 4'd0; x[2] = 4'd1; x[3] = 4'd0;
        x[4] = 4'd1; x[5] = 4'd0; x[6] = 4'd1; x[7] = 4'd0;
        h[0] = 4'd1; h[1] = 4'd0; h[2] = 4'd1; h[3] = 4'd0;
        h[4] = 4'd1; h[5] = 4'd0; h[6] = 4'd1; h[7] = 4'd0;
        #10;

        x[0] = 4'd1; x[1] = 4'd2; x[2] = 4'd3; x[3] = 4'd4;
        x[4] = 4'd5; x[5] = 4'd6; x[6] = 4'd7; x[7] = 4'd8;
        h[0] = 4'd1; h[1] = 4'd1; h[2] = 4'd1; h[3] = 4'd1;
        h[4] = 4'd1; h[5] = 4'd1; h[6] = 4'd1; h[7] = 4'd1;
        #10;

        x[0] = 4'd5; x[1] = 4'd5; x[2] = 4'd5; x[3] = 4'd5;
        x[4] = 4'd5; x[5] = 4'd5; x[6] = 4'd5; x[7] = 4'd5;
        h[0] = 4'd1; h[1] = 4'd2; h[2] = 4'd3; h[3] = 4'd4;
        h[4] = 4'd5; h[5] = 4'd6; h[6] = 4'd7; h[7] = 4'd8;
        #10;

        x[0] = 4'd15; x[1] = 4'd15; x[2] = 4'd15; x[3] = 4'd15;
        x[4] = 4'd15; x[5] = 4'd15; x[6] = 4'd15; x[7] = 4'd15;
        h[0] = 4'd15; h[1] = 4'd15; h[2] = 4'd15; h[3] = 4'd15;
        h[4] = 4'd15; h[5] = 4'd15; h[6] = 4'd15; h[7] = 4'd15;
        #10;

        x[0] = 4'd1; x[1] = 4'd0; x[2] = 4'd0; x[3] = 4'd0;
        x[4] = 4'd0; x[5] = 4'd0; x[6] = 4'd0; x[7] = 4'd0;
        h[0] = 4'd2; h[1] = 4'd3; h[2] = 4'd4; h[3] = 4'd5;
        h[4] = 4'd6; h[5] = 4'd7; h[6] = 4'd8; h[7] = 4'd9;
        #10;

        x[0] = 4'd7; x[1] = 4'd3; x[2] = 4'd9; x[3] = 4'd2;
        x[4] = 4'd5; x[5] = 4'd1; x[6] = 4'd8; x[7] = 4'd4;
        h[0] = 4'd6; h[1] = 4'd2; h[2] = 4'd7; h[3] = 4'd1;
        h[4] = 4'd9; h[5] = 4'd3; h[6] = 4'd5; h[7] = 4'd8;
        #10;

        $finish;
    end

endmodule

verilog/assignments/2/convolution/conv.vcd
$date
	Thu Apr 17 22:07:16 2025
$end
$version
	Icarus Verilog
$end
$timescale
	1ps
$end
$scope module tb_conv $end
$scope module dut $end
$scope begin $ivl_for_loop0 $end
$var integer 32 ! i [31:0] $end
$upscope $end
$scope begin $ivl_for_loop1 $end
$var integer 32 " i [31:0] $end
$scope begin $ivl_for_loop2 $end
$var integer 32 # j [31:0] $end
$upscope $end
$upscope $end
$upscope $end
$upscope $end
$enddefinitions $end
$comment Show the parameter values. $end
$dumpall
$end
#0
$dumpvars
b1000 #
b1000 "
b1111 !
$end
#10000
b1000 #
b1000 "
b1111 !
#20000
b1000 #
b1000 "
b1111 !
#30000
b1000 #
b1000 "
b1111 !
#40000
b1000 #
b1000 "
b1111 !
#50000
b1000 #
b1000 "
b1111 !
#60000
b1000 #
b1000 "
b1111 !
#70000
b1000 #
b1000 "
b1111 !
